vedro_flaky_steps/__init__.py
vedro_flaky_steps/_expected_failure.py
vedro_flaky_steps/_flaky_steps_plugin.py
vedro_flaky_steps/_scheduler.py
vedro_flaky_steps/py.typed
vedro_flaky_steps-1.1.2.dist-info/LICENSE
vedro_flaky_steps-1.1.2.dist-info/METADATA
vedro_flaky_steps-1.1.2.dist-info/WHEEL
vedro_flaky_steps-1.1.2.dist-info/top_level.txt
vedro_flaky_steps-1.1.2.dist-info/RECORD
