Metadata-Version: 2.1
Name: vedro-flaky-steps
Version: 1.1.2
Summary: vedro-flaky-steps plugin for vedro framework
Home-page: https://github.com/miner34006/vedro-flaky-steps
Author: Bogdan Polianok
Author-email: miner34006@gmail.com
License: Apache-2.0
Classifier: License :: OSI Approved :: Apache Software License
Classifier: Programming Language :: Python :: 3.7
Classifier: Programming Language :: Python :: 3.8
Classifier: Programming Language :: Python :: 3.9
Classifier: Programming Language :: Python :: 3.10
Classifier: Programming Language :: Python :: 3.11
Classifier: Typing :: Typed
Requires-Python: >=3.7
License-File: LICENSE
Requires-Dist: vedro <2.0,>=1.7
